README.md
setup.py
st_schema.egg-info/PKG-INFO
st_schema.egg-info/SOURCES.txt
st_schema.egg-info/dependency_links.txt
st_schema.egg-info/top_level.txt
stschema/STBase.py
stschema/__init__.py
stschema/lambdaGenerator.py
stschema/discovery/DiscoveryDevice.py
stschema/discovery/DiscoveryResponse.py
stschema/discovery/__init__.py
stschema/state/CommandResponse.py
stschema/state/StateDevice.py
stschema/state/StateRefreshResponse.py
stschema/state/__init__.py
stschema/utils/__init__.py
stschema/utils/responseBuilder.py