Metadata-Version: 2.1
Name: st-schema
Version: 1.0
Summary: SmartThings Schema helper library for python.
Home-page: https://github.com/SmartThingsCommunity/st-schema-python
Author: SmartThings
Author-email: juan@smartthings.com
License: Apache License 2.0
Download-URL: https://github.com/SmartThingsCommunity/st-schema-python/archive/stschema-1.0.tar.gz
Keywords: smartthings schema cloud c2c st
Platform: UNKNOWN
Classifier: Development Status :: 3 - Alpha
Classifier: Intended Audience :: Developers
Classifier: Topic :: Internet :: WWW/HTTP :: Dynamic Content
Classifier: License :: OSI Approved :: Apache Software License
Classifier: Programming Language :: Python :: 3.4
Classifier: Programming Language :: Python :: 3.5
Classifier: Programming Language :: Python :: 3.6
